iscc_schema/__init__.py
iscc_schema/aliases.json
iscc_schema/base.py
iscc_schema/fields.py
iscc_schema/generator.py
iscc_schema/models/iscc-all.yaml
iscc_schema/models/iscc-basic.yaml
iscc_schema/models/iscc-collection.yaml
iscc_schema/models/iscc-crypto.yaml
iscc_schema/models/iscc-declaration.yaml
iscc_schema/models/iscc-embeddable.yaml
iscc_schema/models/iscc-extended.yaml
iscc_schema/models/iscc-generator.yaml
iscc_schema/models/iscc-jsonld.yaml
iscc_schema/models/iscc-minimal.yaml
iscc_schema/models/iscc-nft.yaml
iscc_schema/models/iscc-technical.yaml
iscc_schema/reference/iscc-generator.yaml
iscc_schema/schema.py
iscc_schema-0.4.0.dist-info/LICENSE
iscc_schema-0.4.0.dist-info/WHEEL
iscc_schema-0.4.0.dist-info/METADATA
iscc_schema-0.4.0.dist-info/RECORD
