Metadata-Version: 2.1
Name: iscc-schema
Version: 0.4.0
Summary: ISCC - JSON-LD Metadata and OpenAPI Service Descriptions
Home-page: https://iscc.codes
License: Apache-2.0
Keywords: iscc,identifier,media,content,hash,blockchain,similarity
Author: Titusz
Author-email: tp@py7.de
Requires-Python: >=3.7,<4.0.0
Classifier: License :: OSI Approved :: Apache Software License
Classifier: Programming Language :: Python :: 3
Classifier: Programming Language :: Python :: 3.7
Classifier: Programming Language :: Python :: 3.8
Classifier: Programming Language :: Python :: 3.9
Classifier: Programming Language :: Python :: 3.10
Requires-Dist: jcs (>=0.2,<0.3)
Requires-Dist: pydantic (>=1.9,<2.0)
Project-URL: Bug Tracker, https://github.com/iscc/iscc-schema/issues
Project-URL: Changelog, https://schema.iscc.codes/changelog
Project-URL: Documentation, https://schema.iscc.codes/
Project-URL: Repository, https://github.com/iscc/iscc-schema
